<odoo>
    <data>
        <record id="mrp_dispatched_list">
            <field name="name">Dispatched</field>
            <field name="model">stock.picking</field>
            <field name="arch" type="xml">
                <tree string="Dispatched Information">
                    <field name="shipping_number" />
                    <field name="charging_mode" />
                    <field name="client_label" />
                    <field name="required_loading_date" />
                </tree>
            </field>
        </record>
    </data>
</odoo>